discrimintools/__init__.py
discrimintools/datasets/__init__.py
discrimintools/datasets/load_alcools.py
discrimintools/datasets/load_autos.py
discrimintools/datasets/load_canines.py
discrimintools/datasets/load_dataset.py
discrimintools/datasets/load_divay.py
discrimintools/datasets/load_heart.py
discrimintools/datasets/load_infidelity.py
discrimintools/datasets/load_mushroom.py
discrimintools/datasets/load_oliveoil.py
discrimintools/datasets/load_vins.py
discrimintools/datasets/load_vote.py
discrimintools/datasets/load_wine.py
discrimintools/datasets/data/alcools.xlsx
discrimintools/datasets/data/autos.xlsx
discrimintools/datasets/data/breast_cancer.xlsx
discrimintools/datasets/data/canines.xlsx
discrimintools/datasets/data/cultivar.xlsx
discrimintools/datasets/data/divay.xlsx
discrimintools/datasets/data/fish.xlsx
discrimintools/datasets/data/heart.xlsx
discrimintools/datasets/data/infidelity.xlsx
discrimintools/datasets/data/iris.csv
discrimintools/datasets/data/mushroom.xlsx
discrimintools/datasets/data/oliveoil.xlsx
discrimintools/datasets/data/sonar.xlsx
discrimintools/datasets/data/vins.xlsx
discrimintools/datasets/data/vote.xlsx
discrimintools/datasets/data/wavenoise.xlsx
discrimintools/datasets/data/wine.xlsx
discrimintools/discriminant_analysis/__init__.py
discrimintools/discriminant_analysis/_base.py
discrimintools/discriminant_analysis/_candisc.py
discrimintools/discriminant_analysis/_cpls.py
discrimintools/discriminant_analysis/_dica.py
discrimintools/discriminant_analysis/_discrim.py
discrimintools/discriminant_analysis/_gfa.py
discrimintools/discriminant_analysis/_gfalda.py
discrimintools/discriminant_analysis/_mda.py
discrimintools/discriminant_analysis/_mpca.py
discrimintools/discriminant_analysis/_plsda.py
discrimintools/discriminant_analysis/_plslda.py
discrimintools/discriminant_analysis/_plslogit.py
discrimintools/discriminant_analysis/_stepdisc.py
discrimintools/discriminant_analysis/functions/__init__.py
discrimintools-0.1.0.dist-info/licenses/LICENSE
discrimintools-0.1.0.dist-info/METADATA
discrimintools-0.1.0.dist-info/WHEEL
discrimintools-0.1.0.dist-info/top_level.txt
discrimintools-0.1.0.dist-info/RECORD
