Metadata-Version: 2.4
Name: discrimintools
Version: 0.1.0
Summary: Python package dedicated to Discriminant Analysis (DA) distributed under the MIT License
Home-page: https://github.com/enfantbenidedieu/discrimintools
Author: Duvérier DJIFACK ZEBAZE
Author-email: djifacklab@gmail.com
Project-URL: Bug Reports, https://github.com/enfantbenidedieu/discrimintools/issues
Project-URL: Source, https://github.com/enfantbenidedieu/discrimintools
Project-URL: Documentation, https://discrimintools.readthedocs.io
Keywords: linear discriminant analysis,quadratic discriminant analysis,disqual,dismix,dica
Classifier: Intended Audience :: Science/Research
Classifier: Intended Audience :: Developers
Classifier: Programming Language :: Python
Classifier: Topic :: Software Development
Classifier: Topic :: Scientific/Engineering
Classifier: License :: OSI Approved :: MIT License
Classifier: Operating System :: OS Independent
Classifier: Programming Language :: Python :: 3
Classifier: Programming Language :: Python :: 3.11
Requires-Python: >=3.11
License-File: LICENSE
Requires-Dist: statsmodels>=0.14.6
Requires-Dist: scikit-learn>=1.8.0
Requires-Dist: openpyxl>=3.1.5
Requires-Dist: tabulate>=0.9.0
Requires-Dist: plotnine>=0.15.1
Requires-Dist: adjustText>=1.3.0
Dynamic: author
Dynamic: author-email
Dynamic: classifier
Dynamic: description
Dynamic: description-content-type
Dynamic: home-page
Dynamic: keywords
Dynamic: license-file
Dynamic: project-url
Dynamic: requires-dist
Dynamic: requires-python
Dynamic: summary
